canvaslms_sync/__init__.py
canvaslms_sync-1.0.0.dist-info/LICENSE
canvaslms_sync-1.0.0.dist-info/METADATA
canvaslms_sync-1.0.0.dist-info/WHEEL
canvaslms_sync-1.0.0.dist-info/entry_points.txt
canvaslms_sync-1.0.0.dist-info/top_level.txt
canvaslms_sync-1.0.0.dist-info/RECORD
