Metadata-Version: 2.1
Name: canvaslms-sync
Version: 1.0.0
Summary: Synchronise a local folder with one in a Canvas LMS course
Home-page: https://github.com/christianp/canvaslms_sync
Author: Christian Lawson-Perfect
Author-email: christian+pypi@lawson-perfect.uk
License: UNKNOWN
Project-URL: Bug Tracker, https://github.com/christianp/canvaslms_sync/issues
Keywords: Canvas,LMS
Platform: UNKNOWN
Classifier: Programming Language :: Python :: 3
Classifier: Programming Language :: Python :: 3.8
Classifier: License :: OSI Approved :: MIT License
Classifier: Operating System :: OS Independent
Requires-Python: >=3.8
License-File: LICENSE
Requires-Dist: canvasapi (>=2.2.0)
